aiodjango-0.1.0.dist-info/RECORD
aiodjango-0.1.0.dist-info/WHEEL
aiodjango-0.1.0.dist-info/METADATA
aiodjango-0.1.0.dist-info/DESCRIPTION.rst
aiodjango-0.1.0.dist-info/top_level.txt
aiodjango-0.1.0.dist-info/metadata.json
aiodjango/api.py
aiodjango/__init__.py
aiodjango/management/__init__.py
aiodjango/management/commands/__init__.py
aiodjango/management/commands/runserver.py
aiodjango/tests/urls.py
aiodjango/tests/test_commands.py
aiodjango/tests/test_api.py
aiodjango/tests/__init__.py
aiodjango/tests/views.py
