Metadata-Version: 2.0
Name: aiodjango
Version: 0.1.0
Summary: Utilities for running async aiohttp based routes in the context of a Django project.
Home-page: https://github.com/mlavin/aiodjango
Author: Mark Lavin
Author-email: markdlavin@gmail.com
License: BSD
Platform: UNKNOWN
Classifier: Development Status :: 3 - Alpha
Classifier: Framework :: Django
Classifier: Intended Audience :: Developers
Classifier: License :: OSI Approved :: BSD License
Classifier: Operating System :: OS Independent
Classifier: Programming Language :: Python
Classifier: Programming Language :: Python :: 3
Classifier: Programming Language :: Python :: 3.4
Classifier: Programming Language :: Python :: 3.5
Classifier: Topic :: Internet :: WWW/HTTP :: Dynamic Content
Requires-Dist: aiohttp (>=0.19.0)
Requires-Dist: aiohttp-wsgi (>=0.3.0)
